[
    {
        "type": "MultipleAnswer",
        "content": "W jakich godzinach na obszarze zabudowanym obowiązuje dopuszczalna prędkość 60 km/h?",
        "imgSrc": "https://mui.com/static/images/cards/contemplative-reptile.jpg",
        "answerOne": "Od 5:00 do 9:00",
        "answerTwo": "Tylko o 11:35 w soboty",
        "answerThree": "Od 23:00 do 6:00",
        "correctAnswer": 0
    },
    {
        "type": "YesOrNo",
        "content": "Czy w razie unieruchomienia pojazdu na przejeździe kolejowym masz obowiązek ostrzec kierującego pojazdem szynowym, jeżeli nie jest możliwie usunięcie pojazdu z tego przejazdu?",
        "imgSrc": "https://dacmwwxjyw.cfolks.pl/files/pytania/Slajd205_cen_1024x576.jpg",
        "correctAnswer": 0
    },
    {
        "type": "YesOrNo",
        "content": "Czy w tej sytuacji, jadąc na wprost, musisz mieć stale włączony lewy kierunkowskaz, ponieważ omijasz zaparkowane pojazdy?",
        "imgSrc": "https://dacmwwxjyw.cfolks.pl/files/pytania/3067D15org.jpg",
        "correctAnswer": 1
    },
    {
        "type": "YesOrNo",
        "content": "Czy w przedstawionej sytuacji wolno Ci poruszać się z włączonymi przednimi światłami przeciwmgłowymi?",
        "imgSrc": "https://dacmwwxjyw.cfolks.pl/files/pytania/IMG_7630d8org.jpg",
        "correctAnswer": 1
    },
    {
        "type": "MultipleAnswer",
        "content": "Czy holowany pojazd ma wpływ na pole widzenia kierowcy?",
        "imgSrc": "https://dacmwwxjyw.cfolks.pl/files/pytania/Slajd_001573_cen_1024x576.jpg",
        "answerOne": "Nie ma żadnego wpływu",
        "answerTwo": "Tylko podczas wykonywania manewru zawracania.",
        "answerThree": "Ma wpływ na ograniczenie pola widzenia.",
        "correctAnswer": 2
    },
    {
        "type": "MultipleAnswer",
        "content": "W przedstawionej sytuacji za widocznym znakiem na drodze ekspresowej dopuszczalna prędkość samochodu osobowego wynosi:",
        "imgSrc": "https://dacmwwxjyw.cfolks.pl/files/pytania/1068ztPIC.jpg",
        "answerOne": "40km/h",
        "answerTwo": "50km/h",
        "answerThree": "60km/h",
        "correctAnswer": 0
    },
    {
        "type": "MultipleAnswer",
        "content": "Czy masz prawo przewozić niemowlaka na kolanach osoby dorosłej?",
        "imgSrc": "https://dacmwwxjyw.cfolks.pl/files/pytania/2C138.jpg",
        "answerOne": "Nie",
        "answerTwo": "Tak, ale tylko na tylnim siedzeniu.",
        "answerThree": "Tak, ale pod warunkiem, że ta osoba korzysta z pasów bezpieczeństwa",
        "correctAnswer": 0
    }
]